{"0": "Core Game Architecture & Roster Systems", "1": "Procedural Isometric Tile Art & Shadow Drawing", "2": "Sanctuary Isometric Camera Projection & Texture Baking", "3": "Sanctuary Interactive Camera Rig & Pan Controller", "4": "Interactive Sanctuary Affordances & Input Handling", "5": "World Map Biomes Generation & Atlas Panel UI", "6": "Sanctuary Resident Pathfinding & Wander Movement", "7": "Base Game Session State & Core Interaction Bindings", "8": "Vault Inspector Panel & Sanctuary Settings UI", "9": "Wyvern Asset Preloading & Atlas Validation", "10": "Mission Scene Combat Loops & Enemy Spawners", "11": "Sanctuary 3D Projection Decor Geometry & Lighting", "12": "App Entry Bootstrap"}